ddrr/__init__.py
ddrr/apps.py
ddrr/filters.py
ddrr/formatters.py
ddrr/loggers.py
ddrr/middleware.py
ddrr/records.py
ddrr/templates/ddrr/default-request.html
ddrr/templates/ddrr/default-response.html
ddrr/templatetags/__init__.py
ddrr/templatetags/ddrr.py
ddrr/utils.py
ddrr-3.1.0.dist-info/LICENSE
ddrr-3.1.0.dist-info/WHEEL
ddrr-3.1.0.dist-info/METADATA
ddrr-3.1.0.dist-info/RECORD
