Metadata-Version: 2.1
Name: ddrr
Version: 3.1.0
Summary: Print request and response headers, body (with pretty-printing), etc.
Home-page: https://github.com/denizdogan/django-debug-requests-responses
Keywords: django,debug,requests,responses,logging
Author: Deniz Dogan
Author-email: denizdogan@users.noreply.github.com
Requires-Python: >=3.7,<4.0
Classifier: Development Status :: 5 - Production/Stable
Classifier: Environment :: Web Environment
Classifier: Framework :: Django
Classifier: Intended Audience :: Developers
Classifier: License :: OSI Approved :: MIT License
Classifier: Operating System :: OS Independent
Classifier: Programming Language :: Python :: 3
Classifier: Programming Language :: Python :: 3.10
Classifier: Programming Language :: Python :: 3.7
Classifier: Programming Language :: Python :: 3.8
Classifier: Programming Language :: Python :: 3.9
Provides-Extra: xml
Requires-Dist: Django (>=2.2)
Requires-Dist: attrs (>=19.1)
Requires-Dist: lxml (>=4.6.3,<5.0.0); extra == "xml"
Project-URL: Repository, https://github.com/denizdogan/django-debug-requests-responses
